{
  "date": "20260329",
  "sentiment": {
    "score": 65,
    "category": "积极",
    "intensity": "中",
    "key_news": [
      "今年前两个月我国电子商务稳定发展，数字消费、产业电商成为增长主动力，网上商品和服务零售额增长9.2%",
      "2026中关村论坛年会促成300多个项目签约，签约总金额超过850亿元人民币，并发布多项重大科技成果",
      "1—2月上合示范区对上合组织其他成员国进出口增长17.6%，机电、高新技术产品出口均实现两位数增长",
      "“十五五”新图景：沿江高铁等跨区域大通道建设加速，预计带动上下游行业增加值增长近1.5万亿元"
    ]
  },
  "trends": {
    "summary": "中国经济呈现高质量发展与区域协调并进趋势，聚焦乡村全面振兴、科技创新驱动、基础设施互联互通和消费升级，同时加强对外开放与安全监管。",
    "policies": [
      "推进乡村全面振兴，加快农业农村现代化",
      "实施'十五五'规划，加强跨区域交通基础设施建设",
      "深化科技创新和产业融合，支持科技成果转化",
      "促进电子商务和数字消费发展",
      "加强食品安全监管和消费者权益保护"
    ],
    "industries": [
      "现代农业与智慧农业",
      "电子商务与数字消费",
      "高端制造业（如高铁、盾构机）",
      "文化旅游与'赏花经济'",
      "科技创新与人工智能"
    ],
    "indicators": [
      "1-2月电子商务网上商品和服务零售额增长9.2%",
      "1-2月上合示范区进出口增长17.6%",
      "农产品网上零售额增长17.6%",
      "智能产品零售额大幅增长（如智能眼镜增长183.5%）"
    ],
    "key_news": [
      "【新思想引领新征程】绘就乡村全面振兴新画卷：强调锚定农业农村现代化，推动农业强国建设，'十五五'规划将加快农业农村现代化单独成篇。",
      "【'十五五'新图景】一路通达 串起经济版图新廊道：报道沿江高铁等重大工程，预计带动上下游行业增加值增长近1.5万亿元，促进区域协调发展。",
      "今年前两个月我国电子商务稳定发展：数字消费和产业电商成为增长主动力，智能产品网上零售额显著增长，显示消费升级趋势。"
    ]
  },
  "recommendations": [
    {
      "industry": "现代农业与智慧农业",
      "reason": "政策推动乡村全面振兴和农业农村现代化，市场对智慧农业技术需求增长，如精准种植、智能灌溉和农业物联网，提升生产效率与可持续性，符合高质量发展趋势。",
      "companies": [
        "隆平高科(000998)",
        "大北农(002385)",
        "中联重科(000157)"
      ],
      "related_news": [
        "国家推进农业科技现代化，智慧农业试点项目增加",
        "农产品电商平台助力乡村消费升级"
      ],
      "risk_level": "中",
      "disclaimer": "投资有风险，仅供参考",
      "recommended_at": "2026-03-29T13:36:19.420555"
    },
    {
      "industry": "高端制造业（如高铁、盾构机）",
      "reason": "'十五五'规划加强跨区域交通基础设施建设，高铁和盾构机等高端装备需求稳定，技术领先和出口增长支撑行业增长，符合科技创新驱动和产业融合方向。",
      "companies": [
        "中国中车(601766)",
        "中铁工业(600528)",
        "三一重工(600031)"
      ],
      "related_news": [
        "高铁网络扩展带动相关制造业订单",
        "盾构机在国内外基建项目中应用广泛"
      ],
      "risk_level": "中",
      "disclaimer": "投资有风险，仅供参考",
      "recommended_at": "2026-03-29T13:36:19.420567"
    },
    {
      "industry": "科技创新与人工智能",
      "reason": "政策深化科技创新和科技成果转化，人工智能在智能制造、消费电子等领域应用加速，市场情绪积极推动技术迭代和投资热度，符合消费升级和高质量发展趋势。",
      "companies": [
        "海康威视(002415)",
        "科大讯飞(002230)",
        "中兴通讯(000063)"
      ],
      "related_news": [
        "AI技术在各行业渗透率提升，政策支持研发投入",
        "智能设备需求增长带动相关公司业绩"
      ],
      "risk_level": "高",
      "disclaimer": "投资有风险，仅供参考",
      "recommended_at": "2026-03-29T13:36:19.420572"
    }
  ],
  "key_news_summaries": [
    "今年前两个月我国电子商务稳定发展，数字消费、产业电商成为增长主动力，网上商品和服务零售额增长9.2%",
    "2026中关村论坛年会促成300多个项目签约，签约总金额超过850亿元人民币，并发布多项重大科技成果",
    "1—2月上合示范区对上合组织其他成员国进出口增长17.6%，机电、高新技术产品出口均实现两位数增长",
    "“十五五”新图景：沿江高铁等跨区域大通道建设加速，预计带动上下游行业增加值增长近1.5万亿元",
    "【新思想引领新征程】绘就乡村全面振兴新画卷：强调锚定农业农村现代化，推动农业强国建设，'十五五'规划将加快农业农村现代化单独成篇。",
    "【'十五五'新图景】一路通达 串起经济版图新廊道：报道沿江高铁等重大工程，预计带动上下游行业增加值增长近1.5万亿元，促进区域协调发展。",
    "今年前两个月我国电子商务稳定发展：数字消费和产业电商成为增长主动力，智能产品网上零售额显著增长，显示消费升级趋势。"
  ],
  "generated_at": "2026-03-29T13:36:19.420642",
  "analysis_version": "1.0.0"
}